envoy/base/checker/__init__.py
envoy/base/checker/checker.py
envoy/base/checker/decorators.py
envoy/base/checker/py.typed
envoy.base.checker-0.1.2.dist-info/METADATA
envoy.base.checker-0.1.2.dist-info/WHEEL
envoy.base.checker-0.1.2.dist-info/namespace_packages.txt
envoy.base.checker-0.1.2.dist-info/top_level.txt
envoy.base.checker-0.1.2.dist-info/RECORD
