Metadata-Version: 2.1
Name: envoy.base.checker
Version: 0.1.2
Summary: "Checker definitions used in Envoy proxy's CI"
Home-page: https://github.com/envoyproxy/pytooling/tree/main/envoy.base.checker
Author: Ryan Northey
Author-email: ryan@synca.io
Maintainer: Ryan Northey
Maintainer-email: ryan@synca.io
License: Apache Software License 2.0
Platform: UNKNOWN
Requires-Dist: abstracts (>=0.0.12)
Requires-Dist: envoy.base.runner (>=0.1.1)
